procaaso_log/__init__.py
procaaso_log/config.py
procaaso_log/enum.py
procaaso_log/formatter.py
procaaso_log/logger.py
procaaso_log/mp/__init__.py
procaaso_log/mp/config.py
procaaso_log/mp/handler.py
procaaso_log/mp/listener.py
procaaso_log/mp/queue.py
procaaso_log/processor/__init__.py
procaaso_log/processor/custom.py
procaaso_log/processor/renderer.py
procaaso_log/processor/sequence.py
procaaso_log/processor/standard.py
procaaso_log/py.typed
procaaso_log/settings.py
procaaso_log/std/__init__.py
procaaso_log/std/config.py
procaaso_log/std/configure.py
procaaso_log/std/dict_config.py
procaaso_log/util.py
procaaso_log-0.3.3.dist-info/METADATA
procaaso_log-0.3.3.dist-info/WHEEL
procaaso_log-0.3.3.dist-info/RECORD
