Metadata-Version: 2.1
Name: procaaso-log
Version: 0.3.3
Summary: Logginng Utility for use within Procaaso Python Control Tasks
Author: ConSynSys Engineering
Author-email: engineering@consynsys.com
Requires-Python: >=3.9,<4.0
Classifier: Programming Language :: Python :: 3
Classifier: Programming Language :: Python :: 3.9
Classifier: Programming Language :: Python :: 3.10
Classifier: Programming Language :: Python :: 3.11
Classifier: Programming Language :: Python :: 3.12
Requires-Dist: pydantic (>=1.10.9,<2.0.0)
Requires-Dist: structlog (>=24.1.0,<25.0.0)
